aiida_cp2k/__init__.py
aiida_cp2k/calculations/__init__.py
aiida_cp2k/parsers/__init__.py
aiida_cp2k/utils/__init__.py
aiida_cp2k/utils/datatype_helpers.py
aiida_cp2k/utils/input_generator.py
aiida_cp2k/utils/parser.py
aiida_cp2k/utils/workchains.py
aiida_cp2k/workchains/__init__.py
aiida_cp2k/workchains/base.py
aiida_cp2k-2.1.1.dist-info/entry_points.txt
aiida_cp2k-2.1.1.dist-info/LICENSE.txt
aiida_cp2k-2.1.1.dist-info/WHEEL
aiida_cp2k-2.1.1.dist-info/METADATA
aiida_cp2k-2.1.1.dist-info/RECORD
