Metadata-Version: 2.3
Name: aiida-cp2k
Version: 2.1.1
Summary: The official AiiDA plugin for CP2K.
Author: The AiiDA team
Requires-Python: >=3.9
Classifier: Development Status :: 5 - Production/Stable
Classifier: Framework :: AiiDA
Classifier: License :: OSI Approved :: MIT License
Classifier: Operating System :: POSIX :: Linux
Classifier: Operating System :: MacOS :: MacOS X
Classifier: Programming Language :: Python :: 3
Requires-Dist: aiida-core>=2.0.0,<3.0.0
Requires-Dist: aiida-gaussian-datatypes
Requires-Dist: ase
Requires-Dist: ruamel.yaml>=0.16.5
Requires-Dist: cp2k-output-tools
Requires-Dist: aiida-pseudo~=1.2
Requires-Dist: upf-to-json>=0.9
Requires-Dist: bumpver==2022.1119 ; extra == "dev"
Requires-Dist: pgtest~=1.3 ; extra == "dev"
Requires-Dist: pytest~=6.0 ; extra == "dev"
Requires-Dist: pytest-cov~=2.11.1 ; extra == "dev"
Requires-Dist: coverage ; extra == "dev"
Requires-Dist: pre-commit~=3.6 ; extra == "dev"
Requires-Dist: sphinx ; extra == "docs"
Requires-Dist: sphinx-rtd-theme ; extra == "docs"
Requires-Dist: sphinxcontrib-contentui ; extra == "docs"
Requires-Dist: sphinxcontrib-details-directive ; extra == "docs"
Project-URL: Homepage, https://github.com/aiidateam/aiida-cp2k
Provides-Extra: dev
Provides-Extra: docs
